{
    "buildingIndex": ["Joinville", "La Rapée"],
    "buildingCodes": ["JO", "LR"],
    "buildings": [
        {
            "zoneCodes": ["V", "B", "R"],
            "sideIndexUpper": ["RER", "BOIS", "MILIEU"],
            "floorIndex": ["3ème étage", "4ème étage"],
            "zoneIndex": ["Zone verte", "Zone bleue", "Zone rouge"],
            "sideIndex": ["RER", "Bois", "Milieu"]
        },
        {
            "zoneCodes": ["V", "B", "R"],
            "sideIndexUpper": ["SEINE", "COURS", "MILIEU"],
            "floorIndex": ["5ème étage", "6ème étage"],
            "zoneIndex": ["Zone verte", "Zone bleue", "Zone rouge"],
            "sideIndex": ["Seine", "Cours", "Milieu"]
        }
    ]
}